jomiel/__init__.py
jomiel/__main__.py
jomiel/app.py
jomiel/cache.py
jomiel/curve.py
jomiel/error.py
jomiel/hypertext.py
jomiel/log.py
jomiel/data/__init__.py
jomiel/data/config/jomiel.yaml
jomiel/data/config/logger/__init__.py
jomiel/data/config/logger/jomiel.yaml
jomiel/dispatcher/__init__.py
jomiel/dispatcher/media.py
jomiel/keygen/__main__.py
jomiel/keygen/app.py
jomiel/plugin/__init__.py
jomiel/plugin/uri.py
jomiel/plugin/media/__init__.py
jomiel/plugin/media/handler.py
jomiel/plugin/media/parser.py
jomiel/plugin/media/youtube/__init__.py
jomiel/plugin/media/youtube/parser.py
jomiel/plugin/media/youtube/uri.py
jomiel/subsys/__init__.py
jomiel/subsys/hypertext.py
jomiel/subsys/log.py
jomiel/subsys/plugin.py
jomiel/subsys/broker/__init__.py
jomiel/subsys/broker/response.py
jomiel/subsys/broker/worker.py
jomiel-1.2.0.dist-info/LICENSE
jomiel-1.2.0.dist-info/METADATA
jomiel-1.2.0.dist-info/NOTICE
jomiel-1.2.0.dist-info/WHEEL
jomiel-1.2.0.dist-info/entry_points.txt
jomiel-1.2.0.dist-info/top_level.txt
jomiel-1.2.0.dist-info/zip-safe
jomiel-1.2.0.dist-info/RECORD
